MANIFEST.in
README.md
setup.py
pieshell/README.md
pieshell/__init__.py
pieshell/environ.py
pieshell/init.py
pieshell/iterio.py
pieshell/log.py
pieshell/module.py
pieshell/ps.py
pieshell/redir.py
pieshell/shell.py
pieshell/tree.py
pieshell/version.py
pieshell.egg-info/PKG-INFO
pieshell.egg-info/SOURCES.txt
pieshell.egg-info/dependency_links.txt
pieshell.egg-info/entry_points.txt
pieshell.egg-info/requires.txt
pieshell.egg-info/top_level.txt
pieshell/monkeypatches/__init__.py
pieshell/monkeypatches/patch_jedi.py
pieshell/pipeline/__init__.py
pieshell/pipeline/base.py
pieshell/pipeline/builtin.py
pieshell/pipeline/builtins.py
pieshell/pipeline/command.py
pieshell/pipeline/function.py
pieshell/pipeline/group.py
pieshell/pipeline/pipe.py
pieshell/pipeline/redirect.py
pieshell/pipeline/running.py
pieshell/resources/default_config.pysh
pieshell/resources/get_completions
pieshell/signalio/__init__.py
pieshell/signalio/manager_asyncio.py
pieshell/signalio/manager_signalfd.py
pieshell/signalio/signalutils.py
pieshell/utils/__init__.py
pieshell/utils/asyncutils.py
pieshell/utils/copy.py
pieshell/utils/jsonutils.py
pieshell/utils/pipe.py
tests/argpipe_pipeline.pysh
tests/bashsource_pipeline.pysh
tests/error_pipeline.pysh
tests/function_pipeline.pysh
tests/simple_pipeline.pysh