Metadata-Version: 2.1
Name: pieshell
Version: 0.2.12
Summary: Pieshell is a Python shell environment that combines the expressiveness of shell pipelines with the power of python iterators. It can be used both as an interactive shell and as an ordinary python module replacing e.g. subprocess.Popen
Home-page: https://github.com/redhog/pieshell
Author: Egil Moeller
Author-email: egil.moller@piratpartiet.se
License: GPL
Keywords: Python shell pipelines suprocess
Platform: UNKNOWN
Provides-Extra: ps
Provides-Extra: linux
